LICENSE
pyzohoapi/__init__.py
pyzohoapi/books.py
pyzohoapi/core/__init__.py
pyzohoapi/core/collection.py
pyzohoapi/core/utils.py
pyzohoapi/exceptions/__init__.py
pyzohoapi/inventory.py
pyzohoapi/objecttypes/__init__.py
pyzohoapi/objecttypes/mixins/CompositeItemOps.py
pyzohoapi/objecttypes/mixins/CustomFields.py
pyzohoapi/objecttypes/mixins/__init__.py
pyzohoapi-1.0.0.dist-info/LICENSE
pyzohoapi-1.0.0.dist-info/METADATA
pyzohoapi-1.0.0.dist-info/WHEEL
pyzohoapi-1.0.0.dist-info/RECORD
