Metadata-Version: 2.1
Name: pyZohoAPI
Version: 1.0.0
Summary: Pythonic access to Zoho APIs in the Finance Plus suite.
Home-page: https://github.com/tdesposito/pyZohoAPI
License: MIT
Keywords: api,zoho api,zoho books,zoho inventory,zoho
Author: Todd Esposito
Author-email: todd@toddesposito.com
Requires-Python: >=3.6,<4.0
Classifier: Development Status :: 4 - Beta
Classifier: Intended Audience :: Developers
Classifier: License :: OSI Approved :: MIT License
Classifier: Programming Language :: Python :: 3
Classifier: Programming Language :: Python :: 3.6
Classifier: Programming Language :: Python :: 3.7
Classifier: Programming Language :: Python :: 3.8
Classifier: Programming Language :: Python :: 3.9
Classifier: Programming Language :: Python :: 3.10
Classifier: Programming Language :: Python :: 3.11
Classifier: Programming Language :: Python :: 3.12
Classifier: Topic :: Software Development :: Libraries :: Python Modules
Requires-Dist: requests (>=2.25.1,<3.0.0)
Requires-Dist: simplejson (>=3.17.5,<4.0.0)
Project-URL: Documentation, https://pyzohoapi.readthedocs.io/en/latest/
Project-URL: Repository, https://github.com/tdesposito/pyZohoAPI
